mmk/__init__.py
mmk/prediction.py
mmk/__pycache__/__init__.cpython-36.pyc
mmk/__pycache__/prediction.cpython-36.pyc
mmk/models/__init__.py
mmk/models/tabular_dataset.py
mmk/models/__pycache__/__init__.cpython-36.pyc
mmk/models/__pycache__/tabular_dataset.cpython-36.pyc
mmkit-0.0.1a0.dist-info/LICENSE
mmkit-0.0.1a0.dist-info/METADATA
mmkit-0.0.1a0.dist-info/WHEEL
mmkit-0.0.1a0.dist-info/top_level.txt
mmkit-0.0.1a0.dist-info/RECORD
